MANIFEST.in
README.rst
requirements.txt
setup.py
python_transifex.egg-info/PKG-INFO
python_transifex.egg-info/SOURCES.txt
python_transifex.egg-info/dependency_links.txt
python_transifex.egg-info/requires.txt
python_transifex.egg-info/top_level.txt
transifex/__init__.py
transifex/api.py
transifex/exceptions.py
transifex/util.py
transifex/version.txt
transifex/tests/__init__.py
transifex/tests/api.py