Metadata-Version: 1.0
Name: python-transifex
Version: 0.1.3
Summary: A python api to transifex
Home-page: https://github.com/jakul/python-transifex
Author: Craig Blaszczyk
Author-email: masterjakul@gmail.com
License: BSD
Download-URL: https://github.com/jakul/python-transifex/downloads
Platform: UNKNOWN
Classifier: Environment :: Web Environment
Classifier: Framework :: Django
Classifier: Intended Audience :: Developers
Classifier: License :: OSI Approved :: BSD License
Classifier: Operating System :: OS Independent
Classifier: Programming Language :: Python
Classifier: Topic :: Software Development :: Libraries :: Python Modules
